bs1200/__init__.py
bs1200/can_frames.py
bs1200/cfg_tools.py
bs1200/configuration.py
bs1200/driver.py
bs1200/tcp_frames.py
bs1200-1.3.6.dist-info/LICENSE
bs1200-1.3.6.dist-info/METADATA
bs1200-1.3.6.dist-info/WHEEL
bs1200-1.3.6.dist-info/top_level.txt
bs1200-1.3.6.dist-info/RECORD
