Metadata-Version: 2.1
Name: bs1200
Version: 1.3.6
Summary: Python interface to the Bloomy BS1200. Supports driver communication via PCAN-USB interface, and Configuration via Ethernet connection
Author-email: Mikhail Kharitonov <mikhail.kharitonov@bloomy.com>
Maintainer-email: Mikhail Kharitonov <mikhail.kharitonov@bloomy.com>
License: BSD 3-Clause License
Classifier: Programming Language :: Python :: 3
Classifier: Programming Language :: Python :: 3.7
Classifier: Programming Language :: Python :: 3.8
Classifier: Programming Language :: Python :: 3.9
Classifier: Programming Language :: Python :: 3.10
Classifier: License :: OSI Approved :: BSD License
Classifier: Operating System :: OS Independent
License-File: LICENSE
Requires-Dist: python-can
Requires-Dist: uptime
Requires-Dist: nisyscfg
Requires-Dist: paramiko
Requires-Dist: scp
